cisco_sdwan/__init__.py
cisco_sdwan/__main__.py
cisco_sdwan/__version__.py
cisco_sdwan/base/__init__.py
cisco_sdwan/base/catalog.py
cisco_sdwan/base/models_base.py
cisco_sdwan/base/models_vmanage.py
cisco_sdwan/base/processor.py
cisco_sdwan/base/rest_api.py
cisco_sdwan/migration/__init__.py
cisco_sdwan/migration/device_migration.py
cisco_sdwan/migration/device_template_recipes.json
cisco_sdwan/migration/feature_migration.py
cisco_sdwan/migration/feature_template_recipes.json
cisco_sdwan/migration/feature_templates/Factory_Default_AAA_CISCO_Template.json
cisco_sdwan/migration/feature_templates/Factory_Default_Global_CISCO_Template.json
cisco_sdwan/tasks/__init__.py
cisco_sdwan/tasks/common.py
cisco_sdwan/tasks/models.py
cisco_sdwan/tasks/utils.py
cisco_sdwan/tasks/validators.py
cisco_sdwan/tasks/implementation/__init__.py
cisco_sdwan/tasks/implementation/_attach_detach.py
cisco_sdwan/tasks/implementation/_backup.py
cisco_sdwan/tasks/implementation/_certificate.py
cisco_sdwan/tasks/implementation/_delete.py
cisco_sdwan/tasks/implementation/_encrypt.py
cisco_sdwan/tasks/implementation/_list.py
cisco_sdwan/tasks/implementation/_migrate.py
cisco_sdwan/tasks/implementation/_report.py
cisco_sdwan/tasks/implementation/_restore.py
cisco_sdwan/tasks/implementation/_show.py
cisco_sdwan/tasks/implementation/_show_template.py
cisco_sdwan/tasks/implementation/_transform.py
cisco_sdwan-1.25.dist-info/METADATA
cisco_sdwan-1.25.dist-info/WHEEL
cisco_sdwan-1.25.dist-info/entry_points.txt
cisco_sdwan-1.25.dist-info/licenses/LICENSE
cisco_sdwan-1.25.dist-info/RECORD
