Metadata-Version: 2.4
Name: cisco-sdwan
Version: 1.25
Summary: Cisco-SDWAN Automation Toolset
Project-URL: Homepage, https://github.com/CiscoDevNet/sastre
Project-URL: Bug Tracker, https://github.com/CiscoDevNet/sastre/issues
Author-email: Marcelo Reis <sastre-support@cisco.com>
License: MIT License
License-File: LICENSE
Keywords: cisco,network,sastre,sdwan,viptela
Classifier: Development Status :: 5 - Production/Stable
Classifier: License :: OSI Approved :: MIT License
Classifier: Operating System :: OS Independent
Classifier: Programming Language :: Python :: 3 :: Only
Classifier: Programming Language :: Python :: 3.9
Classifier: Programming Language :: Python :: 3.10
Classifier: Programming Language :: Python :: 3.11
Classifier: Programming Language :: Python :: 3.12
Classifier: Topic :: System :: Networking
Classifier: Typing :: Typed
Requires-Python: >=3.9
Requires-Dist: pydantic>=2.6
Requires-Dist: pyyaml
Requires-Dist: requests
